{
  "name": "Scriptagher for Windows (64-bit Installer)",
  "platform": "Windows",
  "version": "1.0.0+1",
  "file_name": "ScriptagherSetup.exe",
  "file_size": 10725285,
  "sha256": "cc34e182831deb01cf3a9f932fcb4be5f3d275169f4bfd127dc5686ea00a9c87",
  "download_url": "https://DiegoFCJ.github.io/scriptagher/installers/windows/ScriptagherSetup.exe",
  "format": "EXE",
  "last_updated": "2025-10-20T15:45:44Z",
  "architecture": "x86_64",
  "build_variant": "Release",
  "distribution": "Installer"
}
