{
  "name": "Scriptagher for Android (ARM64-v8a · Debug Build)",
  "platform": "Android",
  "version": "1.0.0+1",
  "file_name": "scriptagher-arm64-v8a-debug.apk",
  "file_size": 80908797,
  "sha256": "8a38790a537b60ce9ad759d78a52c39ee5fd45ac2a4470512f565ab69715348c",
  "download_url": "https://DiegoFCJ.github.io/scriptagher/installers/android/scriptagher-arm64-v8a-debug.apk",
  "format": "APK",
  "last_updated": "2025-10-20T03:08:21Z",
  "architecture": "ARM64-v8a",
  "build_variant": "Debug"
}
